LICENSE
MANIFEST.in
README.rst
setup.cfg
setup.py
django_geolocation.egg-info/PKG-INFO
django_geolocation.egg-info/SOURCES.txt
django_geolocation.egg-info/dependency_links.txt
django_geolocation.egg-info/requires.txt
django_geolocation.egg-info/top_level.txt
geolocation/__init__.py
geolocation/admin.py
geolocation/apps.py
geolocation/models.py
geolocation/urls.py
geolocation/views.py
geolocation/migrations/0001_initial.py
geolocation/migrations/0002_userconnection_num_conn.py
geolocation/migrations/0003_auto_20211017_1700.py
geolocation/migrations/__init__.py
geolocation/static/geolocation/css/style.css
geolocation/templates/geolocation/index.html
geolocation/templates/geolocation/user_history.html
geolocation/tests/__init__.py
geolocation/tests/test_integration_consistency.py
geolocation/tests/test_integration_db.py
geolocation/tests/test_unit_db.py
geolocation/tests/test_unit_request.py